flask_httpauth.py
Flask_HTTPAuth-4.7.0.dist-info/AUTHORS
Flask_HTTPAuth-4.7.0.dist-info/LICENSE
Flask_HTTPAuth-4.7.0.dist-info/METADATA
Flask_HTTPAuth-4.7.0.dist-info/WHEEL
Flask_HTTPAuth-4.7.0.dist-info/top_level.txt
Flask_HTTPAuth-4.7.0.dist-info/RECORD
