Metadata-Version: 2.1
Name: Flask-HTTPAuth
Version: 4.7.0
Summary: HTTP authentication for Flask routes
Home-page: https://github.com/miguelgrinberg/flask-httpauth
Author: Miguel Grinberg
Author-email: miguel.grinberg@gmail.com
Project-URL: Bug Tracker, https://github.com/miguelgrinberg/flask-httpauth/issues
Classifier: Environment :: Web Environment
Classifier: Intended Audience :: Developers
Classifier: Programming Language :: Python :: 3
Classifier: Programming Language :: Python :: Implementation :: MicroPython
Classifier: License :: OSI Approved :: MIT License
Classifier: Operating System :: OS Independent
License-File: LICENSE
License-File: AUTHORS
